Metadata-Version: 2.1
Name: shap2
Version: 0.40.0
Summary: A unified approach to explain the output of any machine learning model.
Home-page: http://github.com/slundberg/shap
Author: Scott Lundberg
Author-email: slund1@cs.washington.edu
License: MIT
Platform: UNKNOWN
Classifier: Programming Language :: Python :: 3
Classifier: Programming Language :: Python :: 3.6
Provides-Extra: plots
Provides-Extra: others
Provides-Extra: docs
Provides-Extra: test
Provides-Extra: all
License-File: LICENSE
